admin_toolkit/__init__.py
admin_toolkit/admin_filters.py
admin_toolkit/admin_mixins.py
admin_toolkit/apps.py
admin_toolkit/widgets.py
admin_toolkit/static/css/admin_buttons.css
admin_toolkit/static/css/admin_floating.css
admin_toolkit/static/img/fh_filter.png
admin_toolkit/static/js/admin_floating.js
admin_toolkit/static/js/jquery.tabSlideOut.v1.3.js
admin_toolkit/templates/admin/change_list_floating_filter.html
admin_toolkit/templates/admin/change_list_with_extrabuttons.html
admin_toolkit/templates/admin/filter_select.html
django_admin_toolkit-0.1.9.dist-info/LICENSE.md
django_admin_toolkit-0.1.9.dist-info/METADATA
django_admin_toolkit-0.1.9.dist-info/WHEEL
django_admin_toolkit-0.1.9.dist-info/top_level.txt
django_admin_toolkit-0.1.9.dist-info/RECORD
